.gitattributes
CONTRIBUTING.md
LICENSE
MANIFEST.in
README.rst
codecov.yml
install
pyproject.toml
setup.py
discordtool/__init__.py
discordtool/__main__.py
discordtool/_typed_dict.py
discordtool/_version.py
discordtool/abc.py
discordtool/activity.py
discordtool/appinfo.py
discordtool/application_role_connection.py
discordtool/asset.py
discordtool/audit_logs.py
discordtool/automod.py
discordtool/backoff.py
discordtool/bot.py
discordtool/channel.py
discordtool/client.py
discordtool/cog.py
discordtool/colour.py
discordtool/components.py
discordtool/context_managers.py
discordtool/embeds.py
discordtool/emoji.py
discordtool/enums.py
discordtool/errors.py
discordtool/file.py
discordtool/flags.py
discordtool/gateway.py
discordtool/guild.py
discordtool/http.py
discordtool/integrations.py
discordtool/interactions.py
discordtool/invite.py
discordtool/iterators.py
discordtool/member.py
discordtool/mentions.py
discordtool/message.py
discordtool/mixins.py
discordtool/object.py
discordtool/oggparse.py
discordtool/opus.py
discordtool/partial_emoji.py
discordtool/permissions.py
discordtool/player.py
discordtool/py.typed
discordtool/raw_models.py
discordtool/reaction.py
discordtool/role.py
discordtool/scheduled_events.py
discordtool/shard.py
discordtool/stage_instance.py
discordtool/state.py
discordtool/sticker.py
discordtool/team.py
discordtool/template.py
discordtool/threads.py
discordtool/user.py
discordtool/utils.py
discordtool/voice_client.py
discordtool/welcome_screen.py
discordtool/widget.py
discordtool.egg-info/PKG-INFO
discordtool.egg-info/SOURCES.txt
discordtool.egg-info/dependency_links.txt
discordtool.egg-info/requires.txt
discordtool.egg-info/top_level.txt
discordtool/bin/libopus-0.x64.dll
discordtool/bin/libopus-0.x86.dll
discordtool/commands/__init__.py
discordtool/commands/context.py
discordtool/commands/core.py
discordtool/commands/options.py
discordtool/commands/permissions.py
discordtool/ext/bridge/__init__.py
discordtool/ext/bridge/bot.py
discordtool/ext/bridge/context.py
discordtool/ext/bridge/core.py
discordtool/ext/commands/__init__.py
discordtool/ext/commands/_types.py
discordtool/ext/commands/bot.py
